django_cloudflare/__init__.py
django_cloudflare/constants.py
django_cloudflare/py.typed
django_cloudflare-0.0.1.dist-info/LICENSE
django_cloudflare-0.0.1.dist-info/WHEEL
django_cloudflare-0.0.1.dist-info/METADATA
django_cloudflare-0.0.1.dist-info/RECORD
