Metadata-Version: 2.1
Name: django-cloudflare
Version: 0.0.1
Summary: A middleware for Django applications using Cloudflare as a proxy. Allows you to extract and access CF headers.
Home-page: https://github.com/tomwojcik/django-cloudflare
License: MIT
Keywords: django,cloudflare
Author: Tom Wojcik
Author-email: django-cloudflare-pkg@tomwojcik.com
Requires-Python: >=3.8.0,<4.0.0
Classifier: Development Status :: 3 - Alpha
Classifier: Intended Audience :: Developers
Classifier: Intended Audience :: Information Technology
Classifier: Intended Audience :: System Administrators
Classifier: License :: OSI Approved :: MIT License
Classifier: Programming Language :: Python :: 3
Classifier: Programming Language :: Python :: 3.8
Classifier: Programming Language :: Python :: 3.9
Classifier: Programming Language :: Python :: 3.10
Classifier: Programming Language :: Python :: 3.11
Classifier: Programming Language :: Python :: 3.10
Classifier: Programming Language :: Python :: 3.8
Classifier: Programming Language :: Python :: 3.9
Classifier: Topic :: Internet
Requires-Dist: django (>=4.1.5,<5.0.0)
Project-URL: Documentation, https://django-cloudflare.readthedocs.io/
Project-URL: Repository, https://github.com/tomwojcik/django-cloudflare
